{"name":"build-javascript","namedChunkGroups":{"polyfill":{"name":"polyfill","assets":[{"name":"webpack-runtime-66c93f9111ed96b71151.js","size":4310},{"name":"polyfill-73adc85d77410682d3d9.js","size":85832}],"filteredAssets":0,"assetsSize":90142,"filteredAuxiliaryAssets":2,"auxiliaryAssetsSize":224251},"app":{"name":"app","assets":[{"name":"webpack-runtime-66c93f9111ed96b71151.js","size":4310},{"name":"framework-7e3339b0961cca2af3b8.js","size":129745},{"name":"styles.0cc917fab550bf50b9f9.css","size":30749},{"name":"app-5e822098cc04ae08ff35.js","size":222810}],"filteredAssets":0,"assetsSize":387614,"filteredAuxiliaryAssets":3,"auxiliaryAssetsSize":1172064},"component---src-pages-404-js":{"name":"component---src-pages-404-js","assets":[{"name":"cb1608f2-887126c2b2dde8ab4bb5.js","size":1553},{"name":"a9a7754c-2bfcf1dd1044dadbb4cb.js","size":3918},{"name":"commons-bc0929883c46b4b0b977.js","size":81998},{"name":"component---src-pages-404-js-60a75251fec59902b1ae.js","size":4955}],"filteredAssets":0,"assetsSize":92424,"filteredAuxiliaryAssets":5,"auxiliaryAssetsSize":2092968},"component---src-pages-about-tsx":{"name":"component---src-pages-about-tsx","assets":[{"name":"cb1608f2-887126c2b2dde8ab4bb5.js","size":1553},{"name":"a9a7754c-2bfcf1dd1044dadbb4cb.js","size":3918},{"name":"commons-bc0929883c46b4b0b977.js","size":81998},{"name":"component---src-pages-about-tsx-d8630ebf04f3a8af67e3.js","size":9731}],"filteredAssets":0,"assetsSize":97200,"filteredAuxiliaryAssets":5,"auxiliaryAssetsSize":2099010},"component---src-pages-index-js":{"name":"component---src-pages-index-js","assets":[{"name":"cb1608f2-887126c2b2dde8ab4bb5.js","size":1553},{"name":"a9a7754c-2bfcf1dd1044dadbb4cb.js","size":3918},{"name":"commons-bc0929883c46b4b0b977.js","size":81998},{"name":"component---src-pages-index-js-4d6b010f73c77cb82547.js","size":7315}],"filteredAssets":0,"assetsSize":94784,"filteredAuxiliaryAssets":5,"auxiliaryAssetsSize":2098557},"component---src-pages-logs-js":{"name":"component---src-pages-logs-js","assets":[{"name":"cb1608f2-887126c2b2dde8ab4bb5.js","size":1553},{"name":"a9a7754c-2bfcf1dd1044dadbb4cb.js","size":3918},{"name":"commons-bc0929883c46b4b0b977.js","size":81998},{"name":"component---src-pages-logs-js-ede678a94ab1aca29447.js","size":6167}],"filteredAssets":0,"assetsSize":93636,"filteredAuxiliaryAssets":5,"auxiliaryAssetsSize":2096117},"component---src-pages-texts-js":{"name":"component---src-pages-texts-js","assets":[{"name":"cb1608f2-887126c2b2dde8ab4bb5.js","size":1553},{"name":"a9a7754c-2bfcf1dd1044dadbb4cb.js","size":3918},{"name":"commons-bc0929883c46b4b0b977.js","size":81998},{"name":"component---src-pages-texts-js-e805574a0ad56341580c.js","size":6198}],"filteredAssets":0,"assetsSize":93667,"filteredAuxiliaryAssets":5,"auxiliaryAssetsSize":2096154},"component---src-pages-using-typescript-tsx":{"name":"component---src-pages-using-typescript-tsx","assets":[{"name":"cb1608f2-887126c2b2dde8ab4bb5.js","size":1553},{"name":"a9a7754c-2bfcf1dd1044dadbb4cb.js","size":3918},{"name":"commons-bc0929883c46b4b0b977.js","size":81998},{"name":"component---src-pages-using-typescript-tsx-b2f4b44ee1ad0a8c2142.js","size":5773}],"filteredAssets":0,"assetsSize":93242,"filteredAuxiliaryAssets":5,"auxiliaryAssetsSize":2094039},"component---src-templates-article-js":{"name":"component---src-templates-article-js","assets":[{"name":"cb1608f2-887126c2b2dde8ab4bb5.js","size":1553},{"name":"a9a7754c-2bfcf1dd1044dadbb4cb.js","size":3918},{"name":"commons-bc0929883c46b4b0b977.js","size":81998},{"name":"component---src-templates-article-js-93ae0286fed3f4b4e927.js","size":17882}],"filteredAssets":0,"assetsSize":105351,"filteredAuxiliaryAssets":5,"auxiliaryAssetsSize":2133242}},"assetsByChunkName":{"polyfill":["webpack-runtime-66c93f9111ed96b71151.js","polyfill-73adc85d77410682d3d9.js"],"app":["webpack-runtime-66c93f9111ed96b71151.js","framework-7e3339b0961cca2af3b8.js","styles.0cc917fab550bf50b9f9.css","app-5e822098cc04ae08ff35.js"],"component---src-pages-404-js":["cb1608f2-887126c2b2dde8ab4bb5.js","a9a7754c-2bfcf1dd1044dadbb4cb.js","commons-bc0929883c46b4b0b977.js","component---src-pages-404-js-60a75251fec59902b1ae.js"],"component---src-pages-about-tsx":["cb1608f2-887126c2b2dde8ab4bb5.js","a9a7754c-2bfcf1dd1044dadbb4cb.js","commons-bc0929883c46b4b0b977.js","component---src-pages-about-tsx-d8630ebf04f3a8af67e3.js"],"component---src-pages-index-js":["cb1608f2-887126c2b2dde8ab4bb5.js","a9a7754c-2bfcf1dd1044dadbb4cb.js","commons-bc0929883c46b4b0b977.js","component---src-pages-index-js-4d6b010f73c77cb82547.js"],"component---src-pages-logs-js":["cb1608f2-887126c2b2dde8ab4bb5.js","a9a7754c-2bfcf1dd1044dadbb4cb.js","commons-bc0929883c46b4b0b977.js","component---src-pages-logs-js-ede678a94ab1aca29447.js"],"component---src-pages-texts-js":["cb1608f2-887126c2b2dde8ab4bb5.js","a9a7754c-2bfcf1dd1044dadbb4cb.js","commons-bc0929883c46b4b0b977.js","component---src-pages-texts-js-e805574a0ad56341580c.js"],"component---src-pages-using-typescript-tsx":["cb1608f2-887126c2b2dde8ab4bb5.js","a9a7754c-2bfcf1dd1044dadbb4cb.js","commons-bc0929883c46b4b0b977.js","component---src-pages-using-typescript-tsx-b2f4b44ee1ad0a8c2142.js"],"component---src-templates-article-js":["cb1608f2-887126c2b2dde8ab4bb5.js","a9a7754c-2bfcf1dd1044dadbb4cb.js","commons-bc0929883c46b4b0b977.js","component---src-templates-article-js-93ae0286fed3f4b4e927.js"]},"childAssetsByChunkName":{}}