{"name":"build-javascript","namedChunkGroups":{"polyfill":{"name":"polyfill","assets":[{"name":"webpack-runtime-a1fb12303d20411d7d9d.js","size":4086},{"name":"polyfill-73adc85d77410682d3d9.js","size":85832}],"filteredAssets":0,"assetsSize":89918,"filteredAuxiliaryAssets":2,"auxiliaryAssetsSize":223861},"app":{"name":"app","assets":[{"name":"webpack-runtime-a1fb12303d20411d7d9d.js","size":4086},{"name":"framework-ad8b0145e3cd40324783.js","size":129736},{"name":"styles.d11413b00b09fb0e6702.css","size":15924},{"name":"app-e59ebeb56c463cc9ed61.js","size":72546}],"filteredAssets":0,"assetsSize":222292,"filteredAuxiliaryAssets":3,"auxiliaryAssetsSize":666918},"component---src-pages-404-js":{"name":"component---src-pages-404-js","assets":[{"name":"commons-133d68f8483aabc90298.js","size":19718},{"name":"component---src-pages-404-js-b18109622f7f16c607a4.js","size":523}],"filteredAssets":0,"assetsSize":20241,"filteredAuxiliaryAssets":2,"auxiliaryAssetsSize":74021},"component---src-pages-about-tsx":{"name":"component---src-pages-about-tsx","assets":[{"name":"commons-133d68f8483aabc90298.js","size":19718},{"name":"component---src-pages-about-tsx-78aabb0164d80f302d91.js","size":665}],"filteredAssets":0,"assetsSize":20383,"filteredAuxiliaryAssets":2,"auxiliaryAssetsSize":74316},"component---src-pages-index-js":{"name":"component---src-pages-index-js","assets":[{"name":"commons-133d68f8483aabc90298.js","size":19718},{"name":"component---src-pages-index-js-a1e5326c0080aa0e85c4.js","size":2805}],"filteredAssets":0,"assetsSize":22523,"filteredAuxiliaryAssets":2,"auxiliaryAssetsSize":79317},"component---src-pages-using-typescript-tsx":{"name":"component---src-pages-using-typescript-tsx","assets":[{"name":"commons-133d68f8483aabc90298.js","size":19718},{"name":"component---src-pages-using-typescript-tsx-f84034b6bf5d939a1929.js","size":1346}],"filteredAssets":0,"assetsSize":21064,"filteredAuxiliaryAssets":2,"auxiliaryAssetsSize":75117},"component---src-templates-blog-post-js":{"name":"component---src-templates-blog-post-js","assets":[{"name":"commons-133d68f8483aabc90298.js","size":19718},{"name":"component---src-templates-blog-post-js-3f2e721f227a222aa327.js","size":1370}],"filteredAssets":0,"assetsSize":21088,"filteredAuxiliaryAssets":2,"auxiliaryAssetsSize":76837}},"assetsByChunkName":{"polyfill":["webpack-runtime-a1fb12303d20411d7d9d.js","polyfill-73adc85d77410682d3d9.js"],"app":["webpack-runtime-a1fb12303d20411d7d9d.js","framework-ad8b0145e3cd40324783.js","styles.d11413b00b09fb0e6702.css","app-e59ebeb56c463cc9ed61.js"],"component---src-pages-404-js":["commons-133d68f8483aabc90298.js","component---src-pages-404-js-b18109622f7f16c607a4.js"],"component---src-pages-about-tsx":["commons-133d68f8483aabc90298.js","component---src-pages-about-tsx-78aabb0164d80f302d91.js"],"component---src-pages-index-js":["commons-133d68f8483aabc90298.js","component---src-pages-index-js-a1e5326c0080aa0e85c4.js"],"component---src-pages-using-typescript-tsx":["commons-133d68f8483aabc90298.js","component---src-pages-using-typescript-tsx-f84034b6bf5d939a1929.js"],"component---src-templates-blog-post-js":["commons-133d68f8483aabc90298.js","component---src-templates-blog-post-js-3f2e721f227a222aa327.js"]},"childAssetsByChunkName":{}}